{
  "schema": {
    "人员": {
      "properties": [
        "员工姓名",
        "员工编号",
        "主任岗岗位",
        "主任岗开始日期",
        "移动电话",
        "固定电话",
        "电子邮箱",
        "使用组织",
        "来源于s_HR",
        "创建组织",
        "数据状态",
        "禁用状态",
        "联系地址",
        "身份证号",
        "主键ID",
        "创建时间",
        "修改时间"
      ],
      "out_relation": [],
      "in_relation": [],
      "sample": {}
    },
    "会计科目": {
      "properties": [
        "编码",
        "名称",
        "助记码",
        "全名",
        "余额方向",
        "往来核算维度",
        "发生额方向",
        "科目类别",
        "核算所有币别",
        "外币核算",
        "核算维度",
        "银行科目",
        "内部往来科目",
        "现金科目",
        "出日记账",
        "不允许手工录入",
        "往来科目",
        "明细科目",
        "现金等价物",
        "期末调汇",
        "管控组织",
        "使用组织",
        "附表项目_减少",
        "附表项目_增加",
        "启用数量金额辅助核算",
        "主表项目_减少",
        "主表项目_增加",
        "描述",
        "数据状态",
        "创建组织",
        "创建人",
        "创建日期",
        "修改人",
        "修改日期",
        "审核人",
        "审核日期",
        "禁用状态",
        "禁用人",
        "禁用日期",
        "系统预置",
        "核算维度_序号",
        "维度",
        "必录类型",
        "主键ID"
      ],
      "out_relation": [],
      "in_relation": [],
      "sample": {}
    },
    "供应商": {
      "properties": [
        "编码",
        "使用组织",
        "名称",
        "简称",
        "供应商分组",
        "审核人",
        "审核日期",
        "数据状态",
        "禁用状态",
        "主键ID",
        "创建时间",
        "修改时间"
      ],
      "out_relation": [],
      "in_relation": [],
      "sample": {}
    },
    "其他往来单位": {
      "properties": [
        "编码",
        "名称",
        "数据状态",
        "禁用状态",
        "主键ID",
        "创建时间",
        "修改时间"
      ],
      "out_relation": [],
      "in_relation": [],
      "sample": {}
    },
    "凭证": {
      "properties": [
        "账簿",
        "日期",
        "会计年度",
        "期间",
        "凭证字",
        "凭证号",
        "摘要",
        "科目编码",
        "科目名称",
        "科目全名",
        "核算维度",
        "币别",
        "汇率类型",
        "汇率",
        "单位",
        "单价",
        "数量",
        "原币金额",
        "借方金额",
        "贷方金额",
        "凭证编号",
        "来源系统",
        "业务类型",
        "审核状态",
        "作废状态",
        "已指定现金流量项目",
        "是否调整期凭证",
        "核算组织",
        "借方总金额",
        "贷方总金额",
        "审核日期",
        "创建日期",
        "过账日期",
        "结算方式",
        "结算号",
        "当前年度",
        "当前期间",
        "转存信息_转入",
        "转存信息_转出",
        "业务日期",
        "业务编号",
        "分录_序号",
        "是否已冲销",
        "主键ID"
      ],
      "out_relation": [],
      "in_relation": [],
      "sample": {}
    },
    "凭证分录": {
      "properties": [
        "账簿",
        "日期",
        "会计年度",
        "期间",
        "凭证字",
        "凭证号",
        "摘要",
        "科目编码",
        "科目名称",
        "科目全名",
        "核算维度",
        "核算维度_费用项目_编码",
        "核算维度_资产类别_编码",
        "核算维度_资产类别_名称",
        "核算维度_费用项目_名称",
        "核算维度_组织机构_编码",
        "核算维度_组织机构_名称",
        "核算维度_物料分组_编码",
        "核算维度_物料分组_名称",
        "核算维度_供应商_编码",
        "核算维度_客户分组_编码",
        "核算维度_客户分组_名称",
        "核算维度_供应商_名称",
        "核算维度_部门_编码",
        "核算维度_工程项目_编码",
        "核算维度_工程项目_名称",
        "核算维度_部门_名称",
        "核算维度_银行账号_编码",
        "核算维度_客户_编码",
        "核算维度_客户_名称",
        "核算维度_银行账号_名称",
        "核算维度_员工_编码",
        "核算维度_成本项目_编码",
        "核算维度_员工_名称",
        "核算维度_成本项目_名称",
        "核算维度_物料_编码",
        "核算维度_其他往来单位_编码",
        "核算维度_其他往来单位_名称",
        "核算维度_物料_名称",
        "核算维度_待摊项目_编码",
        "核算维度_待摊项目_名称",
        "核算维度_长期待摊项目_编码",
        "核算维度_长期待摊项目_名称",
        "币别",
        "汇率类型",
        "汇率",
        "单位",
        "单价",
        "数量",
        "原币金额",
        "借方金额",
        "贷方金额",
        "凭证编号",
        "来源系统",
        "业务类型",
        "审核状态",
        "作废状态",
        "已指定现金流量项目",
        "是否调整期凭证",
        "核算组织",
        "借方总金额",
        "贷方总金额",
        "审核日期",
        "创建日期",
        "过账日期",
        "结算方式",
        "结算号",
        "当前年度",
        "当前期间",
        "转存信息_转入",
        "转存信息_转出",
        "业务日期",
        "业务编号",
        "分录_序号",
        "是否已冲销",
        "分录ID",
        "凭证ID"
      ],
      "out_relation": [],
      "in_relation": [],
      "sample": {}
    },
    "客户": {
      "properties": [
        "客户编码",
        "客户名称",
        "财务原名称",
        "单据状态",
        "禁用状态",
        "创建组织",
        "使用组织",
        "国家",
        "地区",
        "通讯地址",
        "邮政编码",
        "公司网址",
        "注册地址",
        "联系电话",
        "法人代表",
        "注册资本",
        "创立日期",
        "行业",
        "传真",
        "纳税登记号",
        "公司类别",
        "公司性质",
        "公司规模",
        "对应供应商",
        "对应集团客户",
        "默认付款方",
        "不校验可发量",
        "集团客户",
        "集团客户标识",
        "客户类别",
        "对应组织",
        "备注",
        "结算币别",
        "销售部门",
        "销售组",
        "销售员",
        "结算方式",
        "收款条件",
        "价目表",
        "折扣表",
        "运输提前期",
        "税分类",
        "发票类型",
        "默认税率",
        "启用信用管理",
        "客户优先级",
        "创建人",
        "创建日期",
        "修改人",
        "修改日期",
        "审核人",
        "审核日期",
        "禁用人",
        "禁用日期",
        "客户分组",
        "订货平台管理员",
        "发票抬头",
        "开户银行",
        "统一社会信用代码",
        "银行账号",
        "开票联系电话",
        "开票通讯地址",
        "防串货码",
        "地级市",
        "县级市",
        "直供二批",
        "客户状态",
        "所属一批或直供二批",
        "所属一批客户",
        "销售部门省区",
        "千捶夫销售部门",
        "千捶夫业务组",
        "千捶夫业务员",
        "千捶夫省区",
        "销售渠道",
        "开票",
        "客户简称",
        "直供二批下拉列表",
        "合作状态下拉列表",
        "办事处主任",
        "调理品销售部门",
        "调理品业务组",
        "调理品业务员",
        "台烤销售部门",
        "台烤销售组",
        "台烤销售员",
        "是否带客户联",
        "是否是新客户",
        "主键ID",
        "创建时间",
        "修改时间"
      ],
      "out_relation": [],
      "in_relation": [],
      "sample": {}
    },
    "客户分组": {
      "properties": [
        "父节点ID",
        "编码",
        "名称",
        "主键ID",
        "创建时间",
        "修改时间"
      ],
      "out_relation": [],
      "in_relation": [],
      "sample": {}
    },
    "工程项目": {
      "properties": [
        "类别",
        "编码",
        "名称",
        "数据状态",
        "系统预置",
        "备注",
        "主键ID",
        "创建时间",
        "修改时间"
      ],
      "out_relation": [],
      "in_relation": [],
      "sample": {}
    },
    "待摊项目": {
      "properties": [
        "类别",
        "编码",
        "名称",
        "数据状态",
        "系统预置",
        "备注",
        "主键ID",
        "创建时间",
        "修改时间"
      ],
      "out_relation": [],
      "in_relation": [],
      "sample": {}
    },
    "成本项目": {
      "properties": [
        "编码",
        "名称",
        "成本性态",
        "禁用状态",
        "数据状态",
        "主键ID",
        "创建时间",
        "修改时间"
      ],
      "out_relation": [],
      "in_relation": [],
      "sample": {}
    },
    "物料": {
      "properties": [
        "使用组织",
        "编码",
        "物料来源",
        "名称",
        "规格型号",
        "物料分组",
        "物料分组编码",
        "数据状态",
        "禁用状态",
        "物料属性",
        "存货类别",
        "税分类",
        "默认税率",
        "基本单位",
        "允许采购",
        "允许库存",
        "允许委外",
        "允许销售",
        "允许生产",
        "允许资产",
        "条码",
        "毛重",
        "净重",
        "尺寸单位",
        "长",
        "宽",
        "高",
        "重量单位",
        "体积",
        "最小库存_基本单位",
        "安全库存_基本单位",
        "再订货点_基本单位",
        "经济订货批量_基本单位",
        "最大库存_基本单位",
        "配置生产",
        "特征件子项",
        "套件",
        "结算成本价加减价比例",
        "生产车间_基本",
        "订制品品牌",
        "已使用",
        "是否变更中",
        "主键ID"
      ],
      "out_relation": [],
      "in_relation": [],
      "sample": {}
    },
    "物料分组": {
      "properties": [
        "父节点ID",
        "编码",
        "名称",
        "主键ID",
        "创建时间",
        "修改时间"
      ],
      "out_relation": [],
      "in_relation": [],
      "sample": {}
    },
    "科目余额": {
      "properties": [
        "账簿编码",
        "账簿名称",
        "年度",
        "期间",
        "科目编码",
        "科目名称",
        "科目全名",
        "币别",
        "期初原币",
        "期初本位币",
        "本期借方原币",
        "本期借方本位币",
        "本期贷方原币",
        "本期贷方本位币",
        "本年累计借方原币",
        "本年累计借方本位币",
        "本年累计贷方原币",
        "本年累计贷方本位币",
        "期末原币",
        "期末本位币",
        "本期损益原币",
        "本期损益本位币",
        "本年累计损益原币",
        "本年累计损益本位币",
        "供应商编码",
        "供应商名称",
        "部门编码",
        "部门名称",
        "客户编码",
        "客户名称",
        "员工编码",
        "员工名称",
        "物料编码",
        "物料名称",
        "费用项目编码",
        "费用项目名称",
        "资产类别编码",
        "资产类别名称",
        "组织机构编码",
        "组织机构名称",
        "物料分组编码",
        "物料分组名称",
        "银行编码",
        "银行名称",
        "银行账号编码",
        "银行账号名称",
        "其他往来单位编码",
        "其他往来单位名称",
        "项目名称编码",
        "项目名称名称",
        "在建工程项目编码",
        "在建工程项目名称",
        "长期待摊编码",
        "长期待摊名称",
        "无形资产编码",
        "无形资产名称",
        "采购合同编号",
        "采购合同名称",
        "销售合同编号",
        "销售合同名称",
        "股东编码",
        "股东名称",
        "销售员编码",
        "销售员名称",
        "财政项目编码",
        "财政项目名称",
        "存货类别编码",
        "存货类别名称",
        "费用项目_美国编码",
        "费用项目_美国名称",
        "政府补助项目_废弃编码",
        "政府补助项目_废弃名称",
        "子项目名称编码",
        "子项目名称名称",
        "主键ID",
        "待摊项目编码",
        "工程项目编码",
        "成本项目编码",
        "长期待摊项目编码",
        "客户分组编码"
      ],
      "out_relation": [],
      "in_relation": [],
      "sample": {}
    },
    "组织机构": {
      "properties": [
        "编码",
        "名称",
        "形态",
        "核算组织",
        "核算组织类型",
        "所属法人",
        "业务组织",
        "组织职能",
        "数据状态",
        "主键ID",
        "创建时间",
        "修改时间"
      ],
      "out_relation": [],
      "in_relation": [],
      "sample": {}
    },
    "账簿": {
      "properties": [
        "编码",
        "名称",
        "核算体系",
        "核算组织编码",
        "核算组织",
        "科目表",
        "账簿类型",
        "会计政策",
        "记账本位币",
        "默认汇率类型",
        "默认凭证字",
        "财务应付确认方式",
        "财务应收确认方式",
        "会计日历",
        "当前期间",
        "启用期间",
        "初始化状态",
        "数据状态",
        "创建人",
        "创建日期",
        "描述",
        "创建组织",
        "修改人",
        "修改日期",
        "审核人",
        "禁用状态",
        "审核日期",
        "禁用人",
        "禁用日期",
        "系统预置",
        "主键ID"
      ],
      "out_relation": [],
      "in_relation": [],
      "sample": {}
    },
    "费用项目": {
      "properties": [
        "编码",
        "税率",
        "名称",
        "存货成本类别",
        "描述",
        "是否默认",
        "分组",
        "主键ID",
        "创建时间",
        "修改时间"
      ],
      "out_relation": [],
      "in_relation": [],
      "sample": {}
    },
    "资产类别": {
      "properties": [
        "编码",
        "名称",
        "原值包含进项税",
        "默认计量单位",
        "描述",
        "数据状态",
        "主键ID",
        "创建时间",
        "修改时间"
      ],
      "out_relation": [],
      "in_relation": [],
      "sample": {}
    },
    "部门": {
      "properties": [
        "编码",
        "助记码",
        "名称",
        "上级部门",
        "HR部门",
        "来源于s_HR",
        "数据状态",
        "禁用状态",
        "部门全称",
        "创建组织",
        "使用组织",
        "主键ID"
      ],
      "out_relation": [],
      "in_relation": [],
      "sample": {}
    },
    "银行账户": {
      "properties": [
        "使用组织",
        "创建组织",
        "账号类型",
        "银行账号",
        "账户名称",
        "开户银行",
        "银行",
        "资金上划",
        "上划方式",
        "上划定额",
        "留底余额",
        "最小上划金额",
        "数据状态",
        "禁用状态",
        "账户收支属性",
        "内部账户",
        "支持网银",
        "默认账号",
        "启用智能对账",
        "支持自动下载电子回单",
        "支持自动下载当天电子回单",
        "支持电子回单",
        "网上银行类型",
        "主键ID",
        "创建时间",
        "修改时间"
      ],
      "out_relation": [],
      "in_relation": [],
      "sample": {}
    },
    "长期待摊项目": {
      "properties": [
        "类别",
        "编码",
        "名称",
        "数据状态",
        "系统预置",
        "备注",
        "主键ID",
        "创建时间",
        "修改时间"
      ],
      "out_relation": [],
      "in_relation": [],
      "sample": {}
    }
  }
}